{
    "Version": "2012-10-17",
    "Statement": [
        {
            "Sid": "VisualEditor0",
            "Effect": "Allow",
            "Action": [
                "dynamodb:PutItem",
                "dynamodb:DeleteItem",
                "dynamodb:GetItem",
                "dynamodb:Scan",
                "dynamodb:Query",
                "dynamodb:UpdateItem",
                "dynamodb:DeleteTable",
                "dynamodb:UpdateTable"
            ],
            "Resource": [
                "arn:aws:dynamodb:us-east-1:734973700788:table/ROLL_DICE_SIMULATION",
                "arn:aws:dynamodb:*:734973700788:table/*/index/*"
            ]
        },
        {
            "Sid": "VisualEditor1",
            "Effect": "Allow",
            "Action": [
                "dynamodb:PutItem",
                "dynamodb:DeleteItem",
                "dynamodb:GetItem",
                "dynamodb:Scan",
                "dynamodb:Query",
                "dynamodb:UpdateItem",
                "dynamodb:DeleteTable",
                "dynamodb:UpdateTable"
            ],
            "Resource": "arn:aws:dynamodb:us-east-1:734973700788:table/ROLL_DICE_SIMULATION"
        },
        {
            "Sid": "VisualEditor2",
            "Effect": "Allow",
            "Action": [
                "dynamodb:ListContributorInsights",
                "dynamodb:ListGlobalTables",
                "dynamodb:ListTables",
                "dynamodb:ListBackups",
                "dynamodb:ListExports"
            ],
            "Resource": "*"
        }
    ]
}